cubicweb_jsonschema/__init__.py
cubicweb_jsonschema/__pkginfo__.py
cubicweb_jsonschema/predicates.py
cubicweb_jsonschema/resources.py
cubicweb_jsonschema/site_cubicweb.py
cubicweb_jsonschema/testing.py
cubicweb_jsonschema/api/__init__.py
cubicweb_jsonschema/api/entities.py
cubicweb_jsonschema/api/schema.py
cubicweb_jsonschema/entities/__init__.py
cubicweb_jsonschema/entities/ijsonschema.py
cubicweb_jsonschema/i18n/en.po
cubicweb_jsonschema/i18n/fr.po
cubicweb_jsonschema/mappers/__init__.py
cubicweb_jsonschema/mappers/constraints.py
cubicweb_jsonschema/views/__init__.py
cubicweb_jsonschema/views/link.py
cubicweb_jsonschema/views/y2jsl.py
cubicweb_jsonschema-0.2.11.dist-info/METADATA
cubicweb_jsonschema-0.2.11.dist-info/WHEEL
cubicweb_jsonschema-0.2.11.dist-info/entry_points.txt
cubicweb_jsonschema-0.2.11.dist-info/top_level.txt
cubicweb_jsonschema-0.2.11.dist-info/RECORD
