Metadata-Version: 2.1
Name: cubicweb-jsonschema
Version: 0.2.11
Summary: JSON Schema for CubicWeb
Home-page: https://www.cubicweb.org/project/cubicweb-jsonschema
Author: LOGILAB S.A. (Paris, FRANCE)
Author-email: contact@logilab.fr
License: LGPL
Classifier: Environment :: Web Environment
Classifier: Framework :: CubicWeb
Classifier: Programming Language :: Python
Classifier: Programming Language :: Python :: 3
Classifier: Programming Language :: Python :: 3 :: Only
Classifier: Programming Language :: JavaScript
Requires-Python: >=3.7.3
Requires-Dist: cubicweb (<3.39.0,>=3.37.2)
Requires-Dist: iso8601
Requires-Dist: jsl
Requires-Dist: pyramid (>=1.10.8)
